Metadata-Version: 2.1
Name: talkpy
Version: 0.0.1
Summary: It is a very semple libary
Home-page: UNKNOWN
Author: Abir Abedin Khan
Author-email: abirabedinkhan@yahoo.com
License: MIT
Keywords: talkpy
Platform: UNKNOWN
Classifier: Development Status :: 5 - Production/Stable
Classifier: Intended Audience :: Education
Classifier: Operating System :: Microsoft :: Windows :: Windows 10
Classifier: License :: OSI Approved :: MIT License
Classifier: Programming Language :: Python :: 3
